pystepseq/__init__.py
pystepseq/constants.py
pystepseq/help.py
pystepseq/main.py
pystepseq/pystepseq.py
pystepseq/tempotrigger.py
pystepseq/lib/__init__.py
pystepseq/lib/midi_functions.py
pystepseq/lib/pink_noise.py
pystepseq/lib/scales.py
pystepseq-2.0.2.dist-info/LICENSE.txt
pystepseq-2.0.2.dist-info/METADATA
pystepseq-2.0.2.dist-info/WHEEL
pystepseq-2.0.2.dist-info/entry_points.txt
pystepseq-2.0.2.dist-info/top_level.txt
pystepseq-2.0.2.dist-info/RECORD
