Metadata-Version: 2.1
Name: pystepseq
Version: 2.0.2
Summary: A multi-featured commandline interface MIDI step sequencer
Author-email: Aaron Krister Johnson <akjmicro@gmail.com>
License-File: LICENSE.txt
